radicale_imap/__init__.py
radicale_imap-0.2.0.dist-info/LICENSE
radicale_imap-0.2.0.dist-info/METADATA
radicale_imap-0.2.0.dist-info/WHEEL
radicale_imap-0.2.0.dist-info/top_level.txt
radicale_imap-0.2.0.dist-info/RECORD
