Metadata-Version: 2.1
Name: radicale-imap
Version: 0.2.0
Summary: Radicale IMAP authentication plugin
Home-page: https://gitlab.com/comzeradd/radicale-imap/
Author: Nikos Roussos
Author-email: nikos@roussos.cc
License: LICENSE
Platform: UNKNOWN
Classifier: Development Status :: 5 - Production/Stable
Classifier: Environment :: Console
Classifier: License :: OSI Approved :: GNU General Public License v3 (GPLv3)
Classifier: Operating System :: OS Independent
Classifier: Programming Language :: Python :: 3 :: Only
Classifier: Programming Language :: Python :: 3.4
Classifier: Programming Language :: Python :: 3.5
Classifier: Programming Language :: Python :: 3.6
Classifier: Programming Language :: Python :: 3.7
Requires-Dist: radicale
